[
  {
    "xmin": 1378.9559326172,
    "ymin": 992.8295288086,
    "xmax": 1793.9868164062,
    "ymax": 1556.2824707031,
    "confidence": 0.8939378858,
    "class": 0,
    "name": "item"
  },
  {
    "xmin": 1400.5655517578,
    "ymin": 289.969909668,
    "xmax": 1732.7850341797,
    "ymax": 796.2006835938,
    "confidence": 0.8773579001,
    "class": 0,
    "name": "item"
  },
  {
    "xmin": 1860.9339599609,
    "ymin": 1072.4395751953,
    "xmax": 2309.9155273438,
    "ymax": 1521.4196777344,
    "confidence": 0.8632795215,
    "class": 0,
    "name": "item"
  },
  {
    "xmin": 859.0522460938,
    "ymin": 293.0534362793,
    "xmax": 1209.7653808594,
    "ymax": 800.9764404297,
    "confidence": 0.8315624595,
    "class": 0,
    "name": "item"
  },
  {
    "xmin": 330.2766723633,
    "ymin": 266.397277832,
    "xmax": 685.3655395508,
    "ymax": 795.0686035156,
    "confidence": 0.8182428479,
    "class": 0,
    "name": "item"
  },
  {
    "xmin": 1842.646484375,
    "ymin": 327.8665466309,
    "xmax": 2292.4321289062,
    "ymax": 790.0078125,
    "confidence": 0.7868228555,
    "class": 0,
    "name": "item"
  },
  {
    "xmin": 813.2763061523,
    "ymin": 958.6368408203,
    "xmax": 1201.2829589844,
    "ymax": 1547.8060302734,
    "confidence": 0.7639297843,
    "class": 0,
    "name": "item"
  },
  {
    "xmin": 293.0729980469,
    "ymin": 119.6608123779,
    "xmax": 2297.50390625,
    "ymax": 1607.9482421875,
    "confidence": 0.6993734837,
    "class": 0,
    "name": "item"
  },
  {
    "xmin": 326.5174255371,
    "ymin": 973.2507324219,
    "xmax": 719.8706054688,
    "ymax": 1516.4650878906,
    "confidence": 0.6641944051,
    "class": 0,
    "name": "item"
  }
]