[
  {
    "xmin": 327.6157226562,
    "ymin": 187.5203552246,
    "xmax": 1259.9998779297,
    "ymax": 1584.8874511719,
    "confidence": 0.6530053616,
    "class": 0,
    "name": "item"
  },
  {
    "xmin": 799.7551269531,
    "ymin": 274.4093933105,
    "xmax": 1156.7762451172,
    "ymax": 632.0477905273,
    "confidence": 0.4396466613,
    "class": 0,
    "name": "item"
  },
  {
    "xmin": 1288.8017578125,
    "ymin": 100.0124359131,
    "xmax": 2243.6391601562,
    "ymax": 1552.7255859375,
    "confidence": 0.3816866577,
    "class": 0,
    "name": "item"
  },
  {
    "xmin": 875.5205688477,
    "ymin": 771.2492675781,
    "xmax": 1136.0936279297,
    "ymax": 1320.8070068359,
    "confidence": 0.3785001338,
    "class": 0,
    "name": "item"
  },
  {
    "xmin": 466.2749328613,
    "ymin": 823.3938598633,
    "xmax": 753.9107666016,
    "ymax": 1085.1771240234,
    "confidence": 0.3553721905,
    "class": 0,
    "name": "item"
  }
]