[
  {
    "xmin": 1415.8088378906,
    "ymin": 153.7079467773,
    "xmax": 2317.4165039062,
    "ymax": 1561.6083984375,
    "confidence": 0.9183787107,
    "class": 0,
    "name": "item"
  },
  {
    "xmin": 241.4409332275,
    "ymin": 167.3845367432,
    "xmax": 1328.2797851562,
    "ymax": 866.9194335938,
    "confidence": 0.9061760902,
    "class": 0,
    "name": "item"
  },
  {
    "xmin": 245.5172424316,
    "ymin": 881.4743652344,
    "xmax": 1304.0771484375,
    "ymax": 1595.4681396484,
    "confidence": 0.8993802667,
    "class": 0,
    "name": "item"
  }
]