[
  {
    "xmin": 185.6232299805,
    "ymin": 337.3927307129,
    "xmax": 1210.1021728516,
    "ymax": 1348.9002685547,
    "confidence": 0.7611358762,
    "class": 0,
    "name": "item"
  },
  {
    "xmin": 288.9005126953,
    "ymin": 848.5532226562,
    "xmax": 1034.2386474609,
    "ymax": 1283.5,
    "confidence": 0.3284849823,
    "class": 0,
    "name": "item"
  },
  {
    "xmin": 228.2131500244,
    "ymin": 373.9710693359,
    "xmax": 1159.1889648438,
    "ymax": 857.5381469727,
    "confidence": 0.2812848091,
    "class": 0,
    "name": "item"
  },
  {
    "xmin": 1308.0609130859,
    "ymin": 349.132598877,
    "xmax": 2438.6667480469,
    "ymax": 1327.1099853516,
    "confidence": 0.2514235675,
    "class": 0,
    "name": "item"
  }
]