[
  {
    "xmin": 519.0679321289,
    "ymin": 369.987487793,
    "xmax": 859.3670043945,
    "ymax": 620.0050048828,
    "confidence": 0.9203585386,
    "class": 0,
    "name": "item"
  },
  {
    "xmin": 65.3074111938,
    "ymin": 387.6507568359,
    "xmax": 456.069732666,
    "ymax": 627.6315917969,
    "confidence": 0.9108706117,
    "class": 0,
    "name": "item"
  },
  {
    "xmin": 331.5868225098,
    "ymin": 65.5972213745,
    "xmax": 467.971496582,
    "ymax": 336.571105957,
    "confidence": 0.8299780488,
    "class": 0,
    "name": "item"
  },
  {
    "xmin": 41.8817939758,
    "ymin": 78.745300293,
    "xmax": 328.1763000488,
    "ymax": 312.546875,
    "confidence": 0.7289763689,
    "class": 0,
    "name": "item"
  },
  {
    "xmin": 579.5062866211,
    "ymin": 66.5791091919,
    "xmax": 885.5183105469,
    "ymax": 326.3942260742,
    "confidence": 0.4063467085,
    "class": 0,
    "name": "item"
  }
]