[
  {
    "xmin": 275.6054992676,
    "ymin": 123.2948684692,
    "xmax": 1243.1175537109,
    "ymax": 1615.4794921875,
    "confidence": 0.9240725636,
    "class": 0,
    "name": "item"
  },
  {
    "xmin": 1474.3731689453,
    "ymin": 972.5234375,
    "xmax": 1871.3530273438,
    "ymax": 1618.767578125,
    "confidence": 0.8717585206,
    "class": 0,
    "name": "item"
  },
  {
    "xmin": 1892.6257324219,
    "ymin": 979.4298095703,
    "xmax": 2315.3034667969,
    "ymax": 1608.1359863281,
    "confidence": 0.8179653287,
    "class": 0,
    "name": "item"
  },
  {
    "xmin": 1308.5493164062,
    "ymin": 1013.1736450195,
    "xmax": 1469.0682373047,
    "ymax": 1623.0699462891,
    "confidence": 0.5117040873,
    "class": 0,
    "name": "item"
  },
  {
    "xmin": 1625.2247314453,
    "ymin": 114.8397750854,
    "xmax": 2266.6826171875,
    "ymax": 732.6051025391,
    "confidence": 0.4038797915,
    "class": 0,
    "name": "item"
  }
]