[
  {
    "xmin": 750.7756958008,
    "ymin": 446.744140625,
    "xmax": 1370.8161621094,
    "ymax": 1329.0277099609,
    "confidence": 0.8171384335,
    "class": 0,
    "name": "item"
  },
  {
    "xmin": 104.7316360474,
    "ymin": 518.0238647461,
    "xmax": 584.0775146484,
    "ymax": 847.6108398438,
    "confidence": 0.7535409927,
    "class": 0,
    "name": "item"
  },
  {
    "xmin": 1387.0427246094,
    "ymin": 353.0738525391,
    "xmax": 2456.5893554688,
    "ymax": 1411.8278808594,
    "confidence": 0.4791707993,
    "class": 0,
    "name": "item"
  }
]