[
  {
    "xmin": 1391.0588378906,
    "ymin": 118.7565612793,
    "xmax": 2317.6791992188,
    "ymax": 1555.3363037109,
    "confidence": 0.7103180885,
    "class": 0,
    "name": "item"
  },
  {
    "xmin": 280.699798584,
    "ymin": 161.9016571045,
    "xmax": 2309.5405273438,
    "ymax": 1617.0407714844,
    "confidence": 0.6059392095,
    "class": 0,
    "name": "item"
  },
  {
    "xmin": 439.2425231934,
    "ymin": 269.2173461914,
    "xmax": 1222.9234619141,
    "ymax": 1486.1097412109,
    "confidence": 0.4974325597,
    "class": 0,
    "name": "item"
  }
]