[
  {
    "xmin": 247.3026733398,
    "ymin": 91.1440811157,
    "xmax": 509.3074951172,
    "ymax": 953.2489013672,
    "confidence": 0.9012235999,
    "class": 0,
    "name": "item"
  },
  {
    "xmin": 2105.98046875,
    "ymin": 1423.8952636719,
    "xmax": 2222.9340820312,
    "ymax": 1593.4262695312,
    "confidence": 0.8469011784,
    "class": 0,
    "name": "item"
  },
  {
    "xmin": 276.0325317383,
    "ymin": 108.3556594849,
    "xmax": 2435.4711914062,
    "ymax": 1609.1258544922,
    "confidence": 0.5400643349,
    "class": 0,
    "name": "item"
  }
]