[
  {
    "xmin": 714.6895141602,
    "ymin": 429.9388427734,
    "xmax": 1076.2857666016,
    "ymax": 841.5667724609,
    "confidence": 0.7851511836,
    "class": 0,
    "name": "item"
  },
  {
    "xmin": 152.3677062988,
    "ymin": 1048.9989013672,
    "xmax": 522.0451660156,
    "ymax": 1469.7573242188,
    "confidence": 0.706186533,
    "class": 0,
    "name": "item"
  },
  {
    "xmin": 723.6965332031,
    "ymin": 1044.9143066406,
    "xmax": 1091.8541259766,
    "ymax": 1460.3684082031,
    "confidence": 0.6741266251,
    "class": 0,
    "name": "item"
  },
  {
    "xmin": 507.7406005859,
    "ymin": 392.825012207,
    "xmax": 726.6223754883,
    "ymax": 744.3607177734,
    "confidence": 0.6435495019,
    "class": 0,
    "name": "item"
  },
  {
    "xmin": 496.9963989258,
    "ymin": 1148.7291259766,
    "xmax": 740.6417236328,
    "ymax": 1502.4189453125,
    "confidence": 0.4746813476,
    "class": 0,
    "name": "item"
  }
]