[
  {
    "xmin": 865.4906616211,
    "ymin": 1002.8647460938,
    "xmax": 1157.1843261719,
    "ymax": 1504.24609375,
    "confidence": 0.8330267668,
    "class": 0,
    "name": "item"
  },
  {
    "xmin": 403.8359375,
    "ymin": 100.6776199341,
    "xmax": 2252.9389648438,
    "ymax": 1580.1315917969,
    "confidence": 0.4238708317,
    "class": 0,
    "name": "item"
  },
  {
    "xmin": 859.8276367188,
    "ymin": 209.8795318604,
    "xmax": 1158.3275146484,
    "ymax": 914.3775024414,
    "confidence": 0.4166343212,
    "class": 0,
    "name": "item"
  },
  {
    "xmin": 352.6972045898,
    "ymin": 169.8296051025,
    "xmax": 1172.3508300781,
    "ymax": 1567.4499511719,
    "confidence": 0.3968458772,
    "class": 0,
    "name": "item"
  },
  {
    "xmin": 430.4622497559,
    "ymin": 211.0646514893,
    "xmax": 722.0581054688,
    "ymax": 535.4569091797,
    "confidence": 0.3698227406,
    "class": 0,
    "name": "item"
  }
]