[
  {
    "xmin": 575.8856201172,
    "ymin": 518.8603515625,
    "xmax": 973.3591918945,
    "ymax": 1202.8295898438,
    "confidence": 0.5286020041,
    "class": 0,
    "name": "item"
  },
  {
    "xmin": 240.5073547363,
    "ymin": 173.2320098877,
    "xmax": 2337.2282714844,
    "ymax": 1641.8087158203,
    "confidence": 0.4169634581,
    "class": 0,
    "name": "item"
  },
  {
    "xmin": 452.7294311523,
    "ymin": 357.8600769043,
    "xmax": 1144.9071044922,
    "ymax": 1392.7880859375,
    "confidence": 0.3488815129,
    "class": 0,
    "name": "item"
  },
  {
    "xmin": 1310.6623535156,
    "ymin": 229.7015991211,
    "xmax": 2284.6452636719,
    "ymax": 1636.060546875,
    "confidence": 0.2961521447,
    "class": 0,
    "name": "item"
  }
]