[
  {
    "xmin": 55.5052490234,
    "ymin": 330.5648193359,
    "xmax": 453.0442199707,
    "ymax": 632.4374389648,
    "confidence": 0.9250289202,
    "class": 0,
    "name": "item"
  },
  {
    "xmin": 50.3514823914,
    "ymin": 30.6879405975,
    "xmax": 703.9459228516,
    "ymax": 322.7825622559,
    "confidence": 0.9244933724,
    "class": 0,
    "name": "item"
  },
  {
    "xmin": 710.2847290039,
    "ymin": 50.9892234802,
    "xmax": 868.6644287109,
    "ymax": 330.0084228516,
    "confidence": 0.9105272293,
    "class": 0,
    "name": "item"
  },
  {
    "xmin": 459.0272216797,
    "ymin": 330.8463745117,
    "xmax": 851.9337158203,
    "ymax": 634.7083740234,
    "confidence": 0.8743907809,
    "class": 0,
    "name": "item"
  }
]