[
  {
    "xmin": 145.2280578613,
    "ymin": 585.2830200195,
    "xmax": 1541.3206787109,
    "ymax": 2406.3210449219,
    "confidence": 0.8362011909,
    "class": 0,
    "name": "item"
  },
  {
    "xmin": 0.0,
    "ymin": 361.5148925781,
    "xmax": 75.6315917969,
    "ymax": 965.2099609375,
    "confidence": 0.7400957942,
    "class": 0,
    "name": "item"
  },
  {
    "xmin": 0.0,
    "ymin": 1010.2440185547,
    "xmax": 107.1627120972,
    "ymax": 2401.4821777344,
    "confidence": 0.3275006115,
    "class": 0,
    "name": "item"
  }
]