[
  {
    "xmin": 382.071685791,
    "ymin": 1032.0101318359,
    "xmax": 2246.5358886719,
    "ymax": 1639.763671875,
    "confidence": 0.9353328347,
    "class": 0,
    "name": "item"
  },
  {
    "xmin": 514.3441162109,
    "ymin": 150.7782897949,
    "xmax": 1139.9013671875,
    "ymax": 1012.4088745117,
    "confidence": 0.9154930711,
    "class": 0,
    "name": "item"
  },
  {
    "xmin": 1506.1740722656,
    "ymin": 161.7768249512,
    "xmax": 2129.7890625,
    "ymax": 1024.1199951172,
    "confidence": 0.9138602614,
    "class": 0,
    "name": "item"
  }
]