{
  "@context": [
    "http://iiif.io/api/presentation/2/context.json",
    "http://codh.rois.ac.jp/iiif/curation/1/context.json"
  ],
  "@id": "https://nakamura196.github.io/ki2/curation/waseda-i05_01646_0015.json",
  "@type": "cr:Curation",
  "label": "",
  "selections": [
    {
      "@id": "https://nakamura196.github.io/ki2/curation/waseda-i05_01646_0015.json/range",
      "@type": "sc:Range",
      "label": "",
      "members": [
        {
          "@id": "https://nakamura196.github.io/ki2/iiif/waseda-i05_01646_0015/canvas/p8#xywh=211,67,98,506",
          "@type": "sc:Canvas",
          "label": "[1]",
          "metadata": [
            {
              "label": "confidence",
              "value": 0.9244543314
            }
          ],
          "thumbnail": "https://nakamura196.github.io/ki2/files/medium/waseda-i05_01646_0015/00000.jpg"
        },
        {
          "@id": "https://nakamura196.github.io/ki2/iiif/waseda-i05_01646_0015/canvas/p8#xywh=178,145,33,22",
          "@type": "sc:Canvas",
          "label": "[1]",
          "metadata": [
            {
              "label": "confidence",
              "value": 0.4567867815
            }
          ],
          "thumbnail": "https://nakamura196.github.io/ki2/files/medium/waseda-i05_01646_0015/00000.jpg"
        },
        {
          "@id": "https://nakamura196.github.io/ki2/iiif/waseda-i05_01646_0015/canvas/p8#xywh=174,178,47,6",
          "@type": "sc:Canvas",
          "label": "[1]",
          "metadata": [
            {
              "label": "confidence",
              "value": 0.4511114657
            }
          ],
          "thumbnail": "https://nakamura196.github.io/ki2/files/medium/waseda-i05_01646_0015/00000.jpg"
        },
        {
          "@id": "https://nakamura196.github.io/ki2/iiif/waseda-i05_01646_0015/canvas/p7#xywh=54,529,241,109",
          "@type": "sc:Canvas",
          "label": "[2]",
          "metadata": [
            {
              "label": "confidence",
              "value": 0.9165533185
            }
          ],
          "thumbnail": "https://nakamura196.github.io/ki2/files/medium/waseda-i05_01646_0015/00001.jpg"
        },
        {
          "@id": "https://nakamura196.github.io/ki2/iiif/waseda-i05_01646_0015/canvas/p7#xywh=51,49,205,272",
          "@type": "sc:Canvas",
          "label": "[2]",
          "metadata": [
            {
              "label": "confidence",
              "value": 0.9157531261
            }
          ],
          "thumbnail": "https://nakamura196.github.io/ki2/files/medium/waseda-i05_01646_0015/00001.jpg"
        },
        {
          "@id": "https://nakamura196.github.io/ki2/iiif/waseda-i05_01646_0015/canvas/p7#xywh=192,323,72,74",
          "@type": "sc:Canvas",
          "label": "[2]",
          "metadata": [
            {
              "label": "confidence",
              "value": 0.9095405936
            }
          ],
          "thumbnail": "https://nakamura196.github.io/ki2/files/medium/waseda-i05_01646_0015/00001.jpg"
        },
        {
          "@id": "https://nakamura196.github.io/ki2/iiif/waseda-i05_01646_0015/canvas/p7#xywh=257,10,291,396",
          "@type": "sc:Canvas",
          "label": "[2]",
          "metadata": [
            {
              "label": "confidence",
              "value": 0.7037734389
            }
          ],
          "thumbnail": "https://nakamura196.github.io/ki2/files/medium/waseda-i05_01646_0015/00001.jpg"
        },
        {
          "@id": "https://nakamura196.github.io/ki2/iiif/waseda-i05_01646_0015/canvas/p6#xywh=50,382,813,246",
          "@type": "sc:Canvas",
          "label": "[3]",
          "metadata": [
            {
              "label": "confidence",
              "value": 0.9101238251
            }
          ],
          "thumbnail": "https://nakamura196.github.io/ki2/files/medium/waseda-i05_01646_0015/00002.jpg"
        },
        {
          "@id": "https://nakamura196.github.io/ki2/iiif/waseda-i05_01646_0015/canvas/p6#xywh=49,26,35,42",
          "@type": "sc:Canvas",
          "label": "[3]",
          "metadata": [
            {
              "label": "confidence",
              "value": 0.8806321025
            }
          ],
          "thumbnail": "https://nakamura196.github.io/ki2/files/medium/waseda-i05_01646_0015/00002.jpg"
        },
        {
          "@id": "https://nakamura196.github.io/ki2/iiif/waseda-i05_01646_0015/canvas/p6#xywh=86,20,74,48",
          "@type": "sc:Canvas",
          "label": "[3]",
          "metadata": [
            {
              "label": "confidence",
              "value": 0.8682250381
            }
          ],
          "thumbnail": "https://nakamura196.github.io/ki2/files/medium/waseda-i05_01646_0015/00002.jpg"
        },
        {
          "@id": "https://nakamura196.github.io/ki2/iiif/waseda-i05_01646_0015/canvas/p6#xywh=8,28,39,41",
          "@type": "sc:Canvas",
          "label": "[3]",
          "metadata": [
            {
              "label": "confidence",
              "value": 0.8392874002
            }
          ],
          "thumbnail": "https://nakamura196.github.io/ki2/files/medium/waseda-i05_01646_0015/00002.jpg"
        },
        {
          "@id": "https://nakamura196.github.io/ki2/iiif/waseda-i05_01646_0015/canvas/p6#xywh=40,6,45,19",
          "@type": "sc:Canvas",
          "label": "[3]",
          "metadata": [
            {
              "label": "confidence",
              "value": 0.289364934
            }
          ],
          "thumbnail": "https://nakamura196.github.io/ki2/files/medium/waseda-i05_01646_0015/00002.jpg"
        },
        {
          "@id": "https://nakamura196.github.io/ki2/iiif/waseda-i05_01646_0015/canvas/p5#xywh=466,442,226,198",
          "@type": "sc:Canvas",
          "label": "[4]",
          "metadata": [
            {
              "label": "confidence",
              "value": 0.9378194809
            }
          ],
          "thumbnail": "https://nakamura196.github.io/ki2/files/medium/waseda-i05_01646_0015/00003.jpg"
        },
        {
          "@id": "https://nakamura196.github.io/ki2/iiif/waseda-i05_01646_0015/canvas/p5#xywh=35,219,269,200",
          "@type": "sc:Canvas",
          "label": "[4]",
          "metadata": [
            {
              "label": "confidence",
              "value": 0.9377985597
            }
          ],
          "thumbnail": "https://nakamura196.github.io/ki2/files/medium/waseda-i05_01646_0015/00003.jpg"
        },
        {
          "@id": "https://nakamura196.github.io/ki2/iiif/waseda-i05_01646_0015/canvas/p5#xywh=307,153,152,132",
          "@type": "sc:Canvas",
          "label": "[4]",
          "metadata": [
            {
              "label": "confidence",
              "value": 0.9301564693
            }
          ],
          "thumbnail": "https://nakamura196.github.io/ki2/files/medium/waseda-i05_01646_0015/00003.jpg"
        },
        {
          "@id": "https://nakamura196.github.io/ki2/iiif/waseda-i05_01646_0015/canvas/p5#xywh=463,95,120,154",
          "@type": "sc:Canvas",
          "label": "[4]",
          "metadata": [
            {
              "label": "confidence",
              "value": 0.9188889861
            }
          ],
          "thumbnail": "https://nakamura196.github.io/ki2/files/medium/waseda-i05_01646_0015/00003.jpg"
        },
        {
          "@id": "https://nakamura196.github.io/ki2/iiif/waseda-i05_01646_0015/canvas/p5#xywh=462,261,121,166",
          "@type": "sc:Canvas",
          "label": "[4]",
          "metadata": [
            {
              "label": "confidence",
              "value": 0.9117344022
            }
          ],
          "thumbnail": "https://nakamura196.github.io/ki2/files/medium/waseda-i05_01646_0015/00003.jpg"
        },
        {
          "@id": "https://nakamura196.github.io/ki2/iiif/waseda-i05_01646_0015/canvas/p5#xywh=308,28,174,122",
          "@type": "sc:Canvas",
          "label": "[4]",
          "metadata": [
            {
              "label": "confidence",
              "value": 0.892960608
            }
          ],
          "thumbnail": "https://nakamura196.github.io/ki2/files/medium/waseda-i05_01646_0015/00003.jpg"
        },
        {
          "@id": "https://nakamura196.github.io/ki2/iiif/waseda-i05_01646_0015/canvas/p5#xywh=33,22,270,193",
          "@type": "sc:Canvas",
          "label": "[4]",
          "metadata": [
            {
              "label": "confidence",
              "value": 0.8835015893
            }
          ],
          "thumbnail": "https://nakamura196.github.io/ki2/files/medium/waseda-i05_01646_0015/00003.jpg"
        },
        {
          "@id": "https://nakamura196.github.io/ki2/iiif/waseda-i05_01646_0015/canvas/p16#xywh=55,330,397,301",
          "@type": "sc:Canvas",
          "label": "[5]",
          "metadata": [
            {
              "label": "confidence",
              "value": 0.9250289202
            }
          ],
          "thumbnail": "https://nakamura196.github.io/ki2/files/medium/waseda-i05_01646_0015/00004.jpg"
        },
        {
          "@id": "https://nakamura196.github.io/ki2/iiif/waseda-i05_01646_0015/canvas/p16#xywh=19,11,246,110",
          "@type": "sc:Canvas",
          "label": "[5]",
          "metadata": [
            {
              "label": "confidence",
              "value": 0.9244933724
            }
          ],
          "thumbnail": "https://nakamura196.github.io/ki2/files/medium/waseda-i05_01646_0015/00004.jpg"
        },
        {
          "@id": "https://nakamura196.github.io/ki2/iiif/waseda-i05_01646_0015/canvas/p16#xywh=268,19,59,105",
          "@type": "sc:Canvas",
          "label": "[5]",
          "metadata": [
            {
              "label": "confidence",
              "value": 0.9105272293
            }
          ],
          "thumbnail": "https://nakamura196.github.io/ki2/files/medium/waseda-i05_01646_0015/00004.jpg"
        },
        {
          "@id": "https://nakamura196.github.io/ki2/iiif/waseda-i05_01646_0015/canvas/p16#xywh=173,125,148,114",
          "@type": "sc:Canvas",
          "label": "[5]",
          "metadata": [
            {
              "label": "confidence",
              "value": 0.8743907809
            }
          ],
          "thumbnail": "https://nakamura196.github.io/ki2/files/medium/waseda-i05_01646_0015/00004.jpg"
        },
        {
          "@id": "https://nakamura196.github.io/ki2/iiif/waseda-i05_01646_0015/canvas/p15#xywh=637,294,236,350",
          "@type": "sc:Canvas",
          "label": "[6]",
          "metadata": [
            {
              "label": "confidence",
              "value": 0.9102787971
            }
          ],
          "thumbnail": "https://nakamura196.github.io/ki2/files/medium/waseda-i05_01646_0015/00005.jpg"
        },
        {
          "@id": "https://nakamura196.github.io/ki2/iiif/waseda-i05_01646_0015/canvas/p15#xywh=168,125,103,142",
          "@type": "sc:Canvas",
          "label": "[6]",
          "metadata": [
            {
              "label": "confidence",
              "value": 0.8953439593
            }
          ],
          "thumbnail": "https://nakamura196.github.io/ki2/files/medium/waseda-i05_01646_0015/00005.jpg"
        },
        {
          "@id": "https://nakamura196.github.io/ki2/iiif/waseda-i05_01646_0015/canvas/p15#xywh=81,125,88,140",
          "@type": "sc:Canvas",
          "label": "[6]",
          "metadata": [
            {
              "label": "confidence",
              "value": 0.8948121071
            }
          ],
          "thumbnail": "https://nakamura196.github.io/ki2/files/medium/waseda-i05_01646_0015/00005.jpg"
        },
        {
          "@id": "https://nakamura196.github.io/ki2/iiif/waseda-i05_01646_0015/canvas/p15#xywh=24,124,55,75",
          "@type": "sc:Canvas",
          "label": "[6]",
          "metadata": [
            {
              "label": "confidence",
              "value": 0.8505789042
            }
          ],
          "thumbnail": "https://nakamura196.github.io/ki2/files/medium/waseda-i05_01646_0015/00005.jpg"
        },
        {
          "@id": "https://nakamura196.github.io/ki2/iiif/waseda-i05_01646_0015/canvas/p15#xywh=15,7,362,117",
          "@type": "sc:Canvas",
          "label": "[6]",
          "metadata": [
            {
              "label": "confidence",
              "value": 0.8445506096
            }
          ],
          "thumbnail": "https://nakamura196.github.io/ki2/files/medium/waseda-i05_01646_0015/00005.jpg"
        },
        {
          "@id": "https://nakamura196.github.io/ki2/iiif/waseda-i05_01646_0015/canvas/p15#xywh=25,198,52,76",
          "@type": "sc:Canvas",
          "label": "[6]",
          "metadata": [
            {
              "label": "confidence",
              "value": 0.3354434669
            }
          ],
          "thumbnail": "https://nakamura196.github.io/ki2/files/medium/waseda-i05_01646_0015/00005.jpg"
        },
        {
          "@id": "https://nakamura196.github.io/ki2/iiif/waseda-i05_01646_0015/canvas/p14#xywh=231,371,225,283",
          "@type": "sc:Canvas",
          "label": "[7]",
          "metadata": [
            {
              "label": "confidence",
              "value": 0.9338988066
            }
          ],
          "thumbnail": "https://nakamura196.github.io/ki2/files/medium/waseda-i05_01646_0015/00006.jpg"
        },
        {
          "@id": "https://nakamura196.github.io/ki2/iiif/waseda-i05_01646_0015/canvas/p14#xywh=247,123,141,220",
          "@type": "sc:Canvas",
          "label": "[7]",
          "metadata": [
            {
              "label": "confidence",
              "value": 0.9286434054
            }
          ],
          "thumbnail": "https://nakamura196.github.io/ki2/files/medium/waseda-i05_01646_0015/00006.jpg"
        },
        {
          "@id": "https://nakamura196.github.io/ki2/iiif/waseda-i05_01646_0015/canvas/p14#xywh=25,213,95,126",
          "@type": "sc:Canvas",
          "label": "[7]",
          "metadata": [
            {
              "label": "confidence",
              "value": 0.9244583249
            }
          ],
          "thumbnail": "https://nakamura196.github.io/ki2/files/medium/waseda-i05_01646_0015/00006.jpg"
        },
        {
          "@id": "https://nakamura196.github.io/ki2/iiif/waseda-i05_01646_0015/canvas/p14#xywh=22,29,219,176",
          "@type": "sc:Canvas",
          "label": "[7]",
          "metadata": [
            {
              "label": "confidence",
              "value": 0.9226987362
            }
          ],
          "thumbnail": "https://nakamura196.github.io/ki2/files/medium/waseda-i05_01646_0015/00006.jpg"
        },
        {
          "@id": "https://nakamura196.github.io/ki2/iiif/waseda-i05_01646_0015/canvas/p14#xywh=322,20,139,100",
          "@type": "sc:Canvas",
          "label": "[7]",
          "metadata": [
            {
              "label": "confidence",
              "value": 0.9156217575
            }
          ],
          "thumbnail": "https://nakamura196.github.io/ki2/files/medium/waseda-i05_01646_0015/00006.jpg"
        },
        {
          "@id": "https://nakamura196.github.io/ki2/iiif/waseda-i05_01646_0015/canvas/p14#xywh=395,125,65,143",
          "@type": "sc:Canvas",
          "label": "[7]",
          "metadata": [
            {
              "label": "confidence",
              "value": 0.9077329636
            }
          ],
          "thumbnail": "https://nakamura196.github.io/ki2/files/medium/waseda-i05_01646_0015/00006.jpg"
        },
        {
          "@id": "https://nakamura196.github.io/ki2/iiif/waseda-i05_01646_0015/canvas/p14#xywh=242,17,78,100",
          "@type": "sc:Canvas",
          "label": "[7]",
          "metadata": [
            {
              "label": "confidence",
              "value": 0.8429134488
            }
          ],
          "thumbnail": "https://nakamura196.github.io/ki2/files/medium/waseda-i05_01646_0015/00006.jpg"
        },
        {
          "@id": "https://nakamura196.github.io/ki2/iiif/waseda-i05_01646_0015/canvas/p14#xywh=399,270,60,72",
          "@type": "sc:Canvas",
          "label": "[7]",
          "metadata": [
            {
              "label": "confidence",
              "value": 0.8363011479
            }
          ],
          "thumbnail": "https://nakamura196.github.io/ki2/files/medium/waseda-i05_01646_0015/00006.jpg"
        },
        {
          "@id": "https://nakamura196.github.io/ki2/iiif/waseda-i05_01646_0015/canvas/p13#xywh=44,48,411,300",
          "@type": "sc:Canvas",
          "label": "[8]",
          "metadata": [
            {
              "label": "confidence",
              "value": 0.9389045835
            }
          ],
          "thumbnail": "https://nakamura196.github.io/ki2/files/medium/waseda-i05_01646_0015/00007.jpg"
        },
        {
          "@id": "https://nakamura196.github.io/ki2/iiif/waseda-i05_01646_0015/canvas/p13#xywh=73,127,93,109",
          "@type": "sc:Canvas",
          "label": "[8]",
          "metadata": [
            {
              "label": "confidence",
              "value": 0.9304413795
            }
          ],
          "thumbnail": "https://nakamura196.github.io/ki2/files/medium/waseda-i05_01646_0015/00007.jpg"
        },
        {
          "@id": "https://nakamura196.github.io/ki2/iiif/waseda-i05_01646_0015/canvas/p13#xywh=214,148,100,81",
          "@type": "sc:Canvas",
          "label": "[8]",
          "metadata": [
            {
              "label": "confidence",
              "value": 0.9258908629
            }
          ],
          "thumbnail": "https://nakamura196.github.io/ki2/files/medium/waseda-i05_01646_0015/00007.jpg"
        },
        {
          "@id": "https://nakamura196.github.io/ki2/iiif/waseda-i05_01646_0015/canvas/p13#xywh=168,20,149,123",
          "@type": "sc:Canvas",
          "label": "[8]",
          "metadata": [
            {
              "label": "confidence",
              "value": 0.9220453501
            }
          ],
          "thumbnail": "https://nakamura196.github.io/ki2/files/medium/waseda-i05_01646_0015/00007.jpg"
        },
        {
          "@id": "https://nakamura196.github.io/ki2/iiif/waseda-i05_01646_0015/canvas/p13#xywh=16,129,57,105",
          "@type": "sc:Canvas",
          "label": "[8]",
          "metadata": [
            {
              "label": "confidence",
              "value": 0.9069134593
            }
          ],
          "thumbnail": "https://nakamura196.github.io/ki2/files/medium/waseda-i05_01646_0015/00007.jpg"
        },
        {
          "@id": "https://nakamura196.github.io/ki2/iiif/waseda-i05_01646_0015/canvas/p13#xywh=169,139,44,97",
          "@type": "sc:Canvas",
          "label": "[8]",
          "metadata": [
            {
              "label": "confidence",
              "value": 0.8896340132
            }
          ],
          "thumbnail": "https://nakamura196.github.io/ki2/files/medium/waseda-i05_01646_0015/00007.jpg"
        },
        {
          "@id": "https://nakamura196.github.io/ki2/iiif/waseda-i05_01646_0015/canvas/p13#xywh=296,134,17,12",
          "@type": "sc:Canvas",
          "label": "[8]",
          "metadata": [
            {
              "label": "confidence",
              "value": 0.7832279801
            }
          ],
          "thumbnail": "https://nakamura196.github.io/ki2/files/medium/waseda-i05_01646_0015/00007.jpg"
        },
        {
          "@id": "https://nakamura196.github.io/ki2/iiif/waseda-i05_01646_0015/canvas/p24#xywh=491,45,346,438",
          "@type": "sc:Canvas",
          "label": "[9]",
          "metadata": [
            {
              "label": "confidence",
              "value": 0.9160550833
            }
          ],
          "thumbnail": "https://nakamura196.github.io/ki2/files/medium/waseda-i05_01646_0015/00008.jpg"
        },
        {
          "@id": "https://nakamura196.github.io/ki2/iiif/waseda-i05_01646_0015/canvas/p24#xywh=160,167,84,53",
          "@type": "sc:Canvas",
          "label": "[9]",
          "metadata": [
            {
              "label": "confidence",
              "value": 0.9024288654
            }
          ],
          "thumbnail": "https://nakamura196.github.io/ki2/files/medium/waseda-i05_01646_0015/00008.jpg"
        },
        {
          "@id": "https://nakamura196.github.io/ki2/iiif/waseda-i05_01646_0015/canvas/p24#xywh=15,18,144,201",
          "@type": "sc:Canvas",
          "label": "[9]",
          "metadata": [
            {
              "label": "confidence",
              "value": 0.8783584237
            }
          ],
          "thumbnail": "https://nakamura196.github.io/ki2/files/medium/waseda-i05_01646_0015/00008.jpg"
        },
        {
          "@id": "https://nakamura196.github.io/ki2/iiif/waseda-i05_01646_0015/canvas/p24#xywh=17,132,140,87",
          "@type": "sc:Canvas",
          "label": "[9]",
          "metadata": [
            {
              "label": "confidence",
              "value": 0.2647502422
            }
          ],
          "thumbnail": "https://nakamura196.github.io/ki2/files/medium/waseda-i05_01646_0015/00008.jpg"
        },
        {
          "@id": "https://nakamura196.github.io/ki2/iiif/waseda-i05_01646_0015/canvas/p23#xywh=483,188,374,448",
          "@type": "sc:Canvas",
          "label": "[10]",
          "metadata": [
            {
              "label": "confidence",
              "value": 0.9346126914
            }
          ],
          "thumbnail": "https://nakamura196.github.io/ki2/files/medium/waseda-i05_01646_0015/00009.jpg"
        },
        {
          "@id": "https://nakamura196.github.io/ki2/iiif/waseda-i05_01646_0015/canvas/p23#xywh=84,17,67,99",
          "@type": "sc:Canvas",
          "label": "[10]",
          "metadata": [
            {
              "label": "confidence",
              "value": 0.8966622949
            }
          ],
          "thumbnail": "https://nakamura196.github.io/ki2/files/medium/waseda-i05_01646_0015/00009.jpg"
        },
        {
          "@id": "https://nakamura196.github.io/ki2/iiif/waseda-i05_01646_0015/canvas/p23#xywh=175,18,101,39",
          "@type": "sc:Canvas",
          "label": "[10]",
          "metadata": [
            {
              "label": "confidence",
              "value": 0.8938689828
            }
          ],
          "thumbnail": "https://nakamura196.github.io/ki2/files/medium/waseda-i05_01646_0015/00009.jpg"
        },
        {
          "@id": "https://nakamura196.github.io/ki2/iiif/waseda-i05_01646_0015/canvas/p23#xywh=14,18,68,97",
          "@type": "sc:Canvas",
          "label": "[10]",
          "metadata": [
            {
              "label": "confidence",
              "value": 0.8626481295
            }
          ],
          "thumbnail": "https://nakamura196.github.io/ki2/files/medium/waseda-i05_01646_0015/00009.jpg"
        },
        {
          "@id": "https://nakamura196.github.io/ki2/iiif/waseda-i05_01646_0015/canvas/p23#xywh=14,121,133,92",
          "@type": "sc:Canvas",
          "label": "[10]",
          "metadata": [
            {
              "label": "confidence",
              "value": 0.8114449382
            }
          ],
          "thumbnail": "https://nakamura196.github.io/ki2/files/medium/waseda-i05_01646_0015/00009.jpg"
        },
        {
          "@id": "https://nakamura196.github.io/ki2/iiif/waseda-i05_01646_0015/canvas/p22#xywh=488,90,352,475",
          "@type": "sc:Canvas",
          "label": "[11]",
          "metadata": [
            {
              "label": "confidence",
              "value": 0.9367860556
            }
          ],
          "thumbnail": "https://nakamura196.github.io/ki2/files/medium/waseda-i05_01646_0015/00010.jpg"
        },
        {
          "@id": "https://nakamura196.github.io/ki2/iiif/waseda-i05_01646_0015/canvas/p22#xywh=17,10,127,195",
          "@type": "sc:Canvas",
          "label": "[11]",
          "metadata": [
            {
              "label": "confidence",
              "value": 0.8927053213
            }
          ],
          "thumbnail": "https://nakamura196.github.io/ki2/files/medium/waseda-i05_01646_0015/00010.jpg"
        },
        {
          "@id": "https://nakamura196.github.io/ki2/iiif/waseda-i05_01646_0015/canvas/p21#xywh=44,53,409,584",
          "@type": "sc:Canvas",
          "label": "[12]",
          "metadata": [
            {
              "label": "confidence",
              "value": 0.9422221184
            }
          ],
          "thumbnail": "https://nakamura196.github.io/ki2/files/medium/waseda-i05_01646_0015/00011.jpg"
        },
        {
          "@id": "https://nakamura196.github.io/ki2/iiif/waseda-i05_01646_0015/canvas/p21#xywh=120,90,97,64",
          "@type": "sc:Canvas",
          "label": "[12]",
          "metadata": [
            {
              "label": "confidence",
              "value": 0.9010372758
            }
          ],
          "thumbnail": "https://nakamura196.github.io/ki2/files/medium/waseda-i05_01646_0015/00011.jpg"
        },
        {
          "@id": "https://nakamura196.github.io/ki2/iiif/waseda-i05_01646_0015/canvas/p21#xywh=117,21,103,64",
          "@type": "sc:Canvas",
          "label": "[12]",
          "metadata": [
            {
              "label": "confidence",
              "value": 0.8299902081
            }
          ],
          "thumbnail": "https://nakamura196.github.io/ki2/files/medium/waseda-i05_01646_0015/00011.jpg"
        },
        {
          "@id": "https://nakamura196.github.io/ki2/iiif/waseda-i05_01646_0015/canvas/p32#xywh=655,96,182,244",
          "@type": "sc:Canvas",
          "label": "[13]",
          "metadata": [
            {
              "label": "confidence",
              "value": 0.9127284288
            }
          ],
          "thumbnail": "https://nakamura196.github.io/ki2/files/medium/waseda-i05_01646_0015/00012.jpg"
        },
        {
          "@id": "https://nakamura196.github.io/ki2/iiif/waseda-i05_01646_0015/canvas/p32#xywh=36,52,243,345",
          "@type": "sc:Canvas",
          "label": "[13]",
          "metadata": [
            {
              "label": "confidence",
              "value": 0.9055660963
            }
          ],
          "thumbnail": "https://nakamura196.github.io/ki2/files/medium/waseda-i05_01646_0015/00012.jpg"
        },
        {
          "@id": "https://nakamura196.github.io/ki2/iiif/waseda-i05_01646_0015/canvas/p32#xywh=286,56,102,147",
          "@type": "sc:Canvas",
          "label": "[13]",
          "metadata": [
            {
              "label": "confidence",
              "value": 0.8988951445
            }
          ],
          "thumbnail": "https://nakamura196.github.io/ki2/files/medium/waseda-i05_01646_0015/00012.jpg"
        },
        {
          "@id": "https://nakamura196.github.io/ki2/iiif/waseda-i05_01646_0015/canvas/p32#xywh=293,229,213,148",
          "@type": "sc:Canvas",
          "label": "[13]",
          "metadata": [
            {
              "label": "confidence",
              "value": 0.8889766932
            }
          ],
          "thumbnail": "https://nakamura196.github.io/ki2/files/medium/waseda-i05_01646_0015/00012.jpg"
        },
        {
          "@id": "https://nakamura196.github.io/ki2/iiif/waseda-i05_01646_0015/canvas/p31#xywh=109,93,705,264",
          "@type": "sc:Canvas",
          "label": "[14]",
          "metadata": [
            {
              "label": "confidence",
              "value": 0.9355717897
            }
          ],
          "thumbnail": "https://nakamura196.github.io/ki2/files/medium/waseda-i05_01646_0015/00013.jpg"
        },
        {
          "@id": "https://nakamura196.github.io/ki2/iiif/waseda-i05_01646_0015/canvas/p31#xywh=73,77,98,54",
          "@type": "sc:Canvas",
          "label": "[14]",
          "metadata": [
            {
              "label": "confidence",
              "value": 0.907363236
            }
          ],
          "thumbnail": "https://nakamura196.github.io/ki2/files/medium/waseda-i05_01646_0015/00013.jpg"
        },
        {
          "@id": "https://nakamura196.github.io/ki2/iiif/waseda-i05_01646_0015/canvas/p31#xywh=25,78,49,52",
          "@type": "sc:Canvas",
          "label": "[14]",
          "metadata": [
            {
              "label": "confidence",
              "value": 0.7948302627
            }
          ],
          "thumbnail": "https://nakamura196.github.io/ki2/files/medium/waseda-i05_01646_0015/00013.jpg"
        },
        {
          "@id": "https://nakamura196.github.io/ki2/iiif/waseda-i05_01646_0015/canvas/p30#xywh=81,103,748,527",
          "@type": "sc:Canvas",
          "label": "[15]",
          "metadata": [
            {
              "label": "confidence",
              "value": 0.9286430478
            }
          ],
          "thumbnail": "https://nakamura196.github.io/ki2/files/medium/waseda-i05_01646_0015/00014.jpg"
        },
        {
          "@id": "https://nakamura196.github.io/ki2/iiif/waseda-i05_01646_0015/canvas/p29#xywh=106,90,715,522",
          "@type": "sc:Canvas",
          "label": "[16]",
          "metadata": [
            {
              "label": "confidence",
              "value": 0.9425653815
            }
          ],
          "thumbnail": "https://nakamura196.github.io/ki2/files/medium/waseda-i05_01646_0015/00015.jpg"
        },
        {
          "@id": "https://nakamura196.github.io/ki2/iiif/waseda-i05_01646_0015/canvas/p40#xywh=76,106,731,505",
          "@type": "sc:Canvas",
          "label": "[17]",
          "metadata": [
            {
              "label": "confidence",
              "value": 0.9374009967
            }
          ],
          "thumbnail": "https://nakamura196.github.io/ki2/files/medium/waseda-i05_01646_0015/00016.jpg"
        },
        {
          "@id": "https://nakamura196.github.io/ki2/iiif/waseda-i05_01646_0015/canvas/p39#xywh=65,76,794,542",
          "@type": "sc:Canvas",
          "label": "[18]",
          "metadata": [
            {
              "label": "confidence",
              "value": 0.9271999598
            }
          ],
          "thumbnail": "https://nakamura196.github.io/ki2/files/medium/waseda-i05_01646_0015/00017.jpg"
        },
        {
          "@id": "https://nakamura196.github.io/ki2/iiif/waseda-i05_01646_0015/canvas/p38#xywh=268,71,297,237",
          "@type": "sc:Canvas",
          "label": "[19]",
          "metadata": [
            {
              "label": "confidence",
              "value": 0.9271636009
            }
          ],
          "thumbnail": "https://nakamura196.github.io/ki2/files/medium/waseda-i05_01646_0015/00018.jpg"
        },
        {
          "@id": "https://nakamura196.github.io/ki2/iiif/waseda-i05_01646_0015/canvas/p38#xywh=321,203,96,106",
          "@type": "sc:Canvas",
          "label": "[19]",
          "metadata": [
            {
              "label": "confidence",
              "value": 0.9259077907
            }
          ],
          "thumbnail": "https://nakamura196.github.io/ki2/files/medium/waseda-i05_01646_0015/00018.jpg"
        },
        {
          "@id": "https://nakamura196.github.io/ki2/iiif/waseda-i05_01646_0015/canvas/p38#xywh=35,37,95,98",
          "@type": "sc:Canvas",
          "label": "[19]",
          "metadata": [
            {
              "label": "confidence",
              "value": 0.9242199659
            }
          ],
          "thumbnail": "https://nakamura196.github.io/ki2/files/medium/waseda-i05_01646_0015/00018.jpg"
        },
        {
          "@id": "https://nakamura196.github.io/ki2/iiif/waseda-i05_01646_0015/canvas/p38#xywh=234,194,81,128",
          "@type": "sc:Canvas",
          "label": "[19]",
          "metadata": [
            {
              "label": "confidence",
              "value": 0.9234813452
            }
          ],
          "thumbnail": "https://nakamura196.github.io/ki2/files/medium/waseda-i05_01646_0015/00018.jpg"
        },
        {
          "@id": "https://nakamura196.github.io/ki2/iiif/waseda-i05_01646_0015/canvas/p38#xywh=112,169,109,139",
          "@type": "sc:Canvas",
          "label": "[19]",
          "metadata": [
            {
              "label": "confidence",
              "value": 0.9142736793
            }
          ],
          "thumbnail": "https://nakamura196.github.io/ki2/files/medium/waseda-i05_01646_0015/00018.jpg"
        },
        {
          "@id": "https://nakamura196.github.io/ki2/iiif/waseda-i05_01646_0015/canvas/p38#xywh=25,151,82,159",
          "@type": "sc:Canvas",
          "label": "[19]",
          "metadata": [
            {
              "label": "confidence",
              "value": 0.9086549878
            }
          ],
          "thumbnail": "https://nakamura196.github.io/ki2/files/medium/waseda-i05_01646_0015/00018.jpg"
        },
        {
          "@id": "https://nakamura196.github.io/ki2/iiif/waseda-i05_01646_0015/canvas/p38#xywh=290,29,130,159",
          "@type": "sc:Canvas",
          "label": "[19]",
          "metadata": [
            {
              "label": "confidence",
              "value": 0.9013390541
            }
          ],
          "thumbnail": "https://nakamura196.github.io/ki2/files/medium/waseda-i05_01646_0015/00018.jpg"
        },
        {
          "@id": "https://nakamura196.github.io/ki2/iiif/waseda-i05_01646_0015/canvas/p37#xywh=51,128,778,473",
          "@type": "sc:Canvas",
          "label": "[20]",
          "metadata": [
            {
              "label": "confidence",
              "value": 0.9392490983
            }
          ],
          "thumbnail": "https://nakamura196.github.io/ki2/files/medium/waseda-i05_01646_0015/00019.jpg"
        },
        {
          "@id": "https://nakamura196.github.io/ki2/iiif/waseda-i05_01646_0015/canvas/p46#xywh=105,201,738,433",
          "@type": "sc:Canvas",
          "label": "[21]",
          "metadata": [
            {
              "label": "confidence",
              "value": 0.9274853468
            }
          ],
          "thumbnail": "https://nakamura196.github.io/ki2/files/medium/waseda-i05_01646_0015/00020.jpg"
        },
        {
          "@id": "https://nakamura196.github.io/ki2/iiif/waseda-i05_01646_0015/canvas/p46#xywh=8,6,82,31",
          "@type": "sc:Canvas",
          "label": "[21]",
          "metadata": [
            {
              "label": "confidence",
              "value": 0.8872240782
            }
          ],
          "thumbnail": "https://nakamura196.github.io/ki2/files/medium/waseda-i05_01646_0015/00020.jpg"
        },
        {
          "@id": "https://nakamura196.github.io/ki2/iiif/waseda-i05_01646_0015/canvas/p46#xywh=129,6,43,33",
          "@type": "sc:Canvas",
          "label": "[21]",
          "metadata": [
            {
              "label": "confidence",
              "value": 0.8776092529
            }
          ],
          "thumbnail": "https://nakamura196.github.io/ki2/files/medium/waseda-i05_01646_0015/00020.jpg"
        },
        {
          "@id": "https://nakamura196.github.io/ki2/iiif/waseda-i05_01646_0015/canvas/p46#xywh=93,4,35,33",
          "@type": "sc:Canvas",
          "label": "[21]",
          "metadata": [
            {
              "label": "confidence",
              "value": 0.7694261074
            }
          ],
          "thumbnail": "https://nakamura196.github.io/ki2/files/medium/waseda-i05_01646_0015/00020.jpg"
        },
        {
          "@id": "https://nakamura196.github.io/ki2/iiif/waseda-i05_01646_0015/canvas/p45#xywh=51,16,780,631",
          "@type": "sc:Canvas",
          "label": "[22]",
          "metadata": [
            {
              "label": "confidence",
              "value": 0.8136933446
            }
          ],
          "thumbnail": "https://nakamura196.github.io/ki2/files/medium/waseda-i05_01646_0015/00021.jpg"
        },
        {
          "@id": "https://nakamura196.github.io/ki2/iiif/waseda-i05_01646_0015/canvas/p45#xywh=90,11,68,114",
          "@type": "sc:Canvas",
          "label": "[22]",
          "metadata": [
            {
              "label": "confidence",
              "value": 0.2632881999
            }
          ],
          "thumbnail": "https://nakamura196.github.io/ki2/files/medium/waseda-i05_01646_0015/00021.jpg"
        },
        {
          "@id": "https://nakamura196.github.io/ki2/iiif/waseda-i05_01646_0015/canvas/p44#xywh=426,38,464,610",
          "@type": "sc:Canvas",
          "label": "[23]",
          "metadata": [
            {
              "label": "confidence",
              "value": 0.7639093399
            }
          ],
          "thumbnail": "https://nakamura196.github.io/ki2/files/medium/waseda-i05_01646_0015/00022.jpg"
        },
        {
          "@id": "https://nakamura196.github.io/ki2/iiif/waseda-i05_01646_0015/canvas/p54#xywh=4,0,644,969",
          "@type": "sc:Canvas",
          "label": "[24]",
          "metadata": [
            {
              "label": "confidence",
              "value": 0.9454929233
            }
          ],
          "thumbnail": "https://nakamura196.github.io/ki2/files/medium/waseda-i05_01646_0015/00023.jpg"
        },
        {
          "@id": "https://nakamura196.github.io/ki2/iiif/waseda-i05_01646_0015/canvas/p53#xywh=0,22,861,652",
          "@type": "sc:Canvas",
          "label": "[25]",
          "metadata": [
            {
              "label": "confidence",
              "value": 0.9384781718
            }
          ],
          "thumbnail": "https://nakamura196.github.io/ki2/files/medium/waseda-i05_01646_0015/00024.jpg"
        },
        {
          "@id": "https://nakamura196.github.io/ki2/iiif/waseda-i05_01646_0015/canvas/p52#xywh=7,5,633,658",
          "@type": "sc:Canvas",
          "label": "[26]",
          "metadata": [
            {
              "label": "confidence",
              "value": 0.9190781713
            }
          ],
          "thumbnail": "https://nakamura196.github.io/ki2/files/medium/waseda-i05_01646_0015/00025.jpg"
        },
        {
          "@id": "https://nakamura196.github.io/ki2/iiif/waseda-i05_01646_0015/canvas/p51#xywh=37,14,414,979",
          "@type": "sc:Canvas",
          "label": "[27]",
          "metadata": [
            {
              "label": "confidence",
              "value": 0.9051731825
            }
          ],
          "thumbnail": "https://nakamura196.github.io/ki2/files/medium/waseda-i05_01646_0015/00026.jpg"
        },
        {
          "@id": "https://nakamura196.github.io/ki2/iiif/waseda-i05_01646_0015/canvas/p62#xywh=2,27,970,632",
          "@type": "sc:Canvas",
          "label": "[28]",
          "metadata": [
            {
              "label": "confidence",
              "value": 0.9213004708
            }
          ],
          "thumbnail": "https://nakamura196.github.io/ki2/files/medium/waseda-i05_01646_0015/00027.jpg"
        },
        {
          "@id": "https://nakamura196.github.io/ki2/iiif/waseda-i05_01646_0015/canvas/p61#xywh=22,4,412,1014",
          "@type": "sc:Canvas",
          "label": "[29]",
          "metadata": [
            {
              "label": "confidence",
              "value": 0.6927614212
            }
          ],
          "thumbnail": "https://nakamura196.github.io/ki2/files/medium/waseda-i05_01646_0015/00028.jpg"
        },
        {
          "@id": "https://nakamura196.github.io/ki2/iiif/waseda-i05_01646_0015/canvas/p61#xywh=2,100,59,46",
          "@type": "sc:Canvas",
          "label": "[29]",
          "metadata": [
            {
              "label": "confidence",
              "value": 0.6209133863
            }
          ],
          "thumbnail": "https://nakamura196.github.io/ki2/files/medium/waseda-i05_01646_0015/00028.jpg"
        },
        {
          "@id": "https://nakamura196.github.io/ki2/iiif/waseda-i05_01646_0015/canvas/p60#xywh=32,0,611,779",
          "@type": "sc:Canvas",
          "label": "[30]",
          "metadata": [
            {
              "label": "confidence",
              "value": 0.9234429002
            }
          ],
          "thumbnail": "https://nakamura196.github.io/ki2/files/medium/waseda-i05_01646_0015/00029.jpg"
        },
        {
          "@id": "https://nakamura196.github.io/ki2/iiif/waseda-i05_01646_0015/canvas/p59#xywh=28,15,614,694",
          "@type": "sc:Canvas",
          "label": "[31]",
          "metadata": [
            {
              "label": "confidence",
              "value": 0.9183562994
            }
          ],
          "thumbnail": "https://nakamura196.github.io/ki2/files/medium/waseda-i05_01646_0015/00030.jpg"
        },
        {
          "@id": "https://nakamura196.github.io/ki2/iiif/waseda-i05_01646_0015/canvas/p70#xywh=7,2,1001,315",
          "@type": "sc:Canvas",
          "label": "[32]",
          "metadata": [
            {
              "label": "confidence",
              "value": 0.9122505784
            }
          ],
          "thumbnail": "https://nakamura196.github.io/ki2/files/medium/waseda-i05_01646_0015/00031.jpg"
        },
        {
          "@id": "https://nakamura196.github.io/ki2/iiif/waseda-i05_01646_0015/canvas/p69#xywh=34,21,937,642",
          "@type": "sc:Canvas",
          "label": "[33]",
          "metadata": [
            {
              "label": "confidence",
              "value": 0.9309285283
            }
          ],
          "thumbnail": "https://nakamura196.github.io/ki2/files/medium/waseda-i05_01646_0015/00032.jpg"
        },
        {
          "@id": "https://nakamura196.github.io/ki2/iiif/waseda-i05_01646_0015/canvas/p69#xywh=131,59,25,49",
          "@type": "sc:Canvas",
          "label": "[33]",
          "metadata": [
            {
              "label": "confidence",
              "value": 0.8453580141
            }
          ],
          "thumbnail": "https://nakamura196.github.io/ki2/files/medium/waseda-i05_01646_0015/00032.jpg"
        },
        {
          "@id": "https://nakamura196.github.io/ki2/iiif/waseda-i05_01646_0015/canvas/p68#xywh=29,31,617,816",
          "@type": "sc:Canvas",
          "label": "[34]",
          "metadata": [
            {
              "label": "confidence",
              "value": 0.9188862443
            }
          ],
          "thumbnail": "https://nakamura196.github.io/ki2/files/medium/waseda-i05_01646_0015/00033.jpg"
        },
        {
          "@id": "https://nakamura196.github.io/ki2/iiif/waseda-i05_01646_0015/canvas/p67#xywh=17,0,643,758",
          "@type": "sc:Canvas",
          "label": "[35]",
          "metadata": [
            {
              "label": "confidence",
              "value": 0.9285876155
            }
          ],
          "thumbnail": "https://nakamura196.github.io/ki2/files/medium/waseda-i05_01646_0015/00034.jpg"
        },
        {
          "@id": "https://nakamura196.github.io/ki2/iiif/waseda-i05_01646_0015/canvas/p78#xywh=24,0,626,924",
          "@type": "sc:Canvas",
          "label": "[36]",
          "metadata": [
            {
              "label": "confidence",
              "value": 0.9494219422
            }
          ],
          "thumbnail": "https://nakamura196.github.io/ki2/files/medium/waseda-i05_01646_0015/00035.jpg"
        },
        {
          "@id": "https://nakamura196.github.io/ki2/iiif/waseda-i05_01646_0015/canvas/p78#xywh=0,0,3,32",
          "@type": "sc:Canvas",
          "label": "[36]",
          "metadata": [
            {
              "label": "confidence",
              "value": 0.3753190935
            }
          ],
          "thumbnail": "https://nakamura196.github.io/ki2/files/medium/waseda-i05_01646_0015/00035.jpg"
        },
        {
          "@id": "https://nakamura196.github.io/ki2/iiif/waseda-i05_01646_0015/canvas/p77#xywh=23,6,741,666",
          "@type": "sc:Canvas",
          "label": "[37]",
          "metadata": [
            {
              "label": "confidence",
              "value": 0.884655416
            }
          ],
          "thumbnail": "https://nakamura196.github.io/ki2/files/medium/waseda-i05_01646_0015/00036.jpg"
        },
        {
          "@id": "https://nakamura196.github.io/ki2/iiif/waseda-i05_01646_0015/canvas/p76#xywh=14,31,635,908",
          "@type": "sc:Canvas",
          "label": "[38]",
          "metadata": [
            {
              "label": "confidence",
              "value": 0.8546921611
            }
          ],
          "thumbnail": "https://nakamura196.github.io/ki2/files/medium/waseda-i05_01646_0015/00037.jpg"
        },
        {
          "@id": "https://nakamura196.github.io/ki2/iiif/waseda-i05_01646_0015/canvas/p75#xywh=7,10,888,658",
          "@type": "sc:Canvas",
          "label": "[39]",
          "metadata": [
            {
              "label": "confidence",
              "value": 0.9255699515
            }
          ],
          "thumbnail": "https://nakamura196.github.io/ki2/files/medium/waseda-i05_01646_0015/00038.jpg"
        },
        {
          "@id": "https://nakamura196.github.io/ki2/iiif/waseda-i05_01646_0015/canvas/p94#xywh=22,11,562,1009",
          "@type": "sc:Canvas",
          "label": "[40]",
          "metadata": [
            {
              "label": "confidence",
              "value": 0.8886043429
            }
          ],
          "thumbnail": "https://nakamura196.github.io/ki2/files/medium/waseda-i05_01646_0015/00039.jpg"
        },
        {
          "@id": "https://nakamura196.github.io/ki2/iiif/waseda-i05_01646_0015/canvas/p93#xywh=3,0,1004,415",
          "@type": "sc:Canvas",
          "label": "[41]",
          "metadata": [
            {
              "label": "confidence",
              "value": 0.8814448714
            }
          ],
          "thumbnail": "https://nakamura196.github.io/ki2/files/medium/waseda-i05_01646_0015/00040.jpg"
        },
        {
          "@id": "https://nakamura196.github.io/ki2/iiif/waseda-i05_01646_0015/canvas/p92#xywh=18,26,478,367",
          "@type": "sc:Canvas",
          "label": "[42]",
          "metadata": [
            {
              "label": "confidence",
              "value": 0.915269196
            }
          ],
          "thumbnail": "https://nakamura196.github.io/ki2/files/medium/waseda-i05_01646_0015/00041.jpg"
        },
        {
          "@id": "https://nakamura196.github.io/ki2/iiif/waseda-i05_01646_0015/canvas/p92#xywh=158,8,139,114",
          "@type": "sc:Canvas",
          "label": "[42]",
          "metadata": [
            {
              "label": "confidence",
              "value": 0.9021142721
            }
          ],
          "thumbnail": "https://nakamura196.github.io/ki2/files/medium/waseda-i05_01646_0015/00041.jpg"
        },
        {
          "@id": "https://nakamura196.github.io/ki2/iiif/waseda-i05_01646_0015/canvas/p91#xywh=0,5,1024,368",
          "@type": "sc:Canvas",
          "label": "[43]",
          "metadata": [
            {
              "label": "confidence",
              "value": 0.9147905111
            }
          ],
          "thumbnail": "https://nakamura196.github.io/ki2/files/medium/waseda-i05_01646_0015/00042.jpg"
        },
        {
          "@id": "https://nakamura196.github.io/ki2/iiif/waseda-i05_01646_0015/canvas/p102#xywh=24,0,619,969",
          "@type": "sc:Canvas",
          "label": "[44]",
          "metadata": [
            {
              "label": "confidence",
              "value": 0.9461373091
            }
          ],
          "thumbnail": "https://nakamura196.github.io/ki2/files/medium/waseda-i05_01646_0015/00043.jpg"
        },
        {
          "@id": "https://nakamura196.github.io/ki2/iiif/waseda-i05_01646_0015/canvas/p101#xywh=27,27,829,639",
          "@type": "sc:Canvas",
          "label": "[45]",
          "metadata": [
            {
              "label": "confidence",
              "value": 0.9359250069
            }
          ],
          "thumbnail": "https://nakamura196.github.io/ki2/files/medium/waseda-i05_01646_0015/00044.jpg"
        },
        {
          "@id": "https://nakamura196.github.io/ki2/iiif/waseda-i05_01646_0015/canvas/p101#xywh=5,14,66,103",
          "@type": "sc:Canvas",
          "label": "[45]",
          "metadata": [
            {
              "label": "confidence",
              "value": 0.8752397895
            }
          ],
          "thumbnail": "https://nakamura196.github.io/ki2/files/medium/waseda-i05_01646_0015/00044.jpg"
        },
        {
          "@id": "https://nakamura196.github.io/ki2/iiif/waseda-i05_01646_0015/canvas/p100#xywh=23,47,831,566",
          "@type": "sc:Canvas",
          "label": "[46]",
          "metadata": [
            {
              "label": "confidence",
              "value": 0.9256011844
            }
          ],
          "thumbnail": "https://nakamura196.github.io/ki2/files/medium/waseda-i05_01646_0015/00045.jpg"
        },
        {
          "@id": "https://nakamura196.github.io/ki2/iiif/waseda-i05_01646_0015/canvas/p99#xywh=28,3,634,901",
          "@type": "sc:Canvas",
          "label": "[47]",
          "metadata": [
            {
              "label": "confidence",
              "value": 0.9383129478
            }
          ],
          "thumbnail": "https://nakamura196.github.io/ki2/files/medium/waseda-i05_01646_0015/00046.jpg"
        },
        {
          "@id": "https://nakamura196.github.io/ki2/iiif/waseda-i05_01646_0015/canvas/p110#xywh=23,7,866,640",
          "@type": "sc:Canvas",
          "label": "[48]",
          "metadata": [
            {
              "label": "confidence",
              "value": 0.93471241
            }
          ],
          "thumbnail": "https://nakamura196.github.io/ki2/files/medium/waseda-i05_01646_0015/00047.jpg"
        },
        {
          "@id": "https://nakamura196.github.io/ki2/iiif/waseda-i05_01646_0015/canvas/p109#xywh=34,15,439,996",
          "@type": "sc:Canvas",
          "label": "[49]",
          "metadata": [
            {
              "label": "confidence",
              "value": 0.9130647182
            }
          ],
          "thumbnail": "https://nakamura196.github.io/ki2/files/medium/waseda-i05_01646_0015/00048.jpg"
        },
        {
          "@id": "https://nakamura196.github.io/ki2/iiif/waseda-i05_01646_0015/canvas/p108#xywh=12,0,639,1022",
          "@type": "sc:Canvas",
          "label": "[50]",
          "metadata": [
            {
              "label": "confidence",
              "value": 0.9255186319
            }
          ],
          "thumbnail": "https://nakamura196.github.io/ki2/files/medium/waseda-i05_01646_0015/00049.jpg"
        },
        {
          "@id": "https://nakamura196.github.io/ki2/iiif/waseda-i05_01646_0015/canvas/p107#xywh=0,0,810,660",
          "@type": "sc:Canvas",
          "label": "[51]",
          "metadata": [
            {
              "label": "confidence",
              "value": 0.9076763988
            }
          ],
          "thumbnail": "https://nakamura196.github.io/ki2/files/medium/waseda-i05_01646_0015/00050.jpg"
        },
        {
          "@id": "https://nakamura196.github.io/ki2/iiif/waseda-i05_01646_0015/canvas/p107#xywh=66,117,81,8",
          "@type": "sc:Canvas",
          "label": "[51]",
          "metadata": [
            {
              "label": "confidence",
              "value": 0.3517134488
            }
          ],
          "thumbnail": "https://nakamura196.github.io/ki2/files/medium/waseda-i05_01646_0015/00050.jpg"
        },
        {
          "@id": "https://nakamura196.github.io/ki2/iiif/waseda-i05_01646_0015/canvas/p118#xywh=27,4,621,786",
          "@type": "sc:Canvas",
          "label": "[52]",
          "metadata": [
            {
              "label": "confidence",
              "value": 0.914891541
            }
          ],
          "thumbnail": "https://nakamura196.github.io/ki2/files/medium/waseda-i05_01646_0015/00051.jpg"
        },
        {
          "@id": "https://nakamura196.github.io/ki2/iiif/waseda-i05_01646_0015/canvas/p117#xywh=13,10,855,642",
          "@type": "sc:Canvas",
          "label": "[53]",
          "metadata": [
            {
              "label": "confidence",
              "value": 0.9277489781
            }
          ],
          "thumbnail": "https://nakamura196.github.io/ki2/files/medium/waseda-i05_01646_0015/00052.jpg"
        },
        {
          "@id": "https://nakamura196.github.io/ki2/iiif/waseda-i05_01646_0015/canvas/p116#xywh=9,0,813,655",
          "@type": "sc:Canvas",
          "label": "[54]",
          "metadata": [
            {
              "label": "confidence",
              "value": 0.8871341348
            }
          ],
          "thumbnail": "https://nakamura196.github.io/ki2/files/medium/waseda-i05_01646_0015/00053.jpg"
        },
        {
          "@id": "https://nakamura196.github.io/ki2/iiif/waseda-i05_01646_0015/canvas/p116#xywh=5,116,42,9",
          "@type": "sc:Canvas",
          "label": "[54]",
          "metadata": [
            {
              "label": "confidence",
              "value": 0.2834433317
            }
          ],
          "thumbnail": "https://nakamura196.github.io/ki2/files/medium/waseda-i05_01646_0015/00053.jpg"
        },
        {
          "@id": "https://nakamura196.github.io/ki2/iiif/waseda-i05_01646_0015/canvas/p115#xywh=0,7,890,675",
          "@type": "sc:Canvas",
          "label": "[55]",
          "metadata": [
            {
              "label": "confidence",
              "value": 0.9189304113
            }
          ],
          "thumbnail": "https://nakamura196.github.io/ki2/files/medium/waseda-i05_01646_0015/00054.jpg"
        },
        {
          "@id": "https://nakamura196.github.io/ki2/iiif/waseda-i05_01646_0015/canvas/p126#xywh=0,46,983,636",
          "@type": "sc:Canvas",
          "label": "[56]",
          "metadata": [
            {
              "label": "confidence",
              "value": 0.9115964174
            }
          ],
          "thumbnail": "https://nakamura196.github.io/ki2/files/medium/waseda-i05_01646_0015/00055.jpg"
        },
        {
          "@id": "https://nakamura196.github.io/ki2/iiif/waseda-i05_01646_0015/canvas/p125#xywh=39,28,775,630",
          "@type": "sc:Canvas",
          "label": "[57]",
          "metadata": [
            {
              "label": "confidence",
              "value": 0.9271413684
            }
          ],
          "thumbnail": "https://nakamura196.github.io/ki2/files/medium/waseda-i05_01646_0015/00056.jpg"
        },
        {
          "@id": "https://nakamura196.github.io/ki2/iiif/waseda-i05_01646_0015/canvas/p124#xywh=37,0,427,1024",
          "@type": "sc:Canvas",
          "label": "[58]",
          "metadata": [
            {
              "label": "confidence",
              "value": 0.8738288879
            }
          ],
          "thumbnail": "https://nakamura196.github.io/ki2/files/medium/waseda-i05_01646_0015/00057.jpg"
        },
        {
          "@id": "https://nakamura196.github.io/ki2/iiif/waseda-i05_01646_0015/canvas/p123#xywh=0,2,914,661",
          "@type": "sc:Canvas",
          "label": "[59]",
          "metadata": [
            {
              "label": "confidence",
              "value": 0.9358154535
            }
          ],
          "thumbnail": "https://nakamura196.github.io/ki2/files/medium/waseda-i05_01646_0015/00058.jpg"
        },
        {
          "@id": "https://nakamura196.github.io/ki2/iiif/waseda-i05_01646_0015/canvas/p134#xywh=15,0,636,798",
          "@type": "sc:Canvas",
          "label": "[60]",
          "metadata": [
            {
              "label": "confidence",
              "value": 0.872969985
            }
          ],
          "thumbnail": "https://nakamura196.github.io/ki2/files/medium/waseda-i05_01646_0015/00059.jpg"
        },
        {
          "@id": "https://nakamura196.github.io/ki2/iiif/waseda-i05_01646_0015/canvas/p133#xywh=19,14,510,992",
          "@type": "sc:Canvas",
          "label": "[61]",
          "metadata": [
            {
              "label": "confidence",
              "value": 0.8963783979
            }
          ],
          "thumbnail": "https://nakamura196.github.io/ki2/files/medium/waseda-i05_01646_0015/00060.jpg"
        },
        {
          "@id": "https://nakamura196.github.io/ki2/iiif/waseda-i05_01646_0015/canvas/p132#xywh=15,18,819,642",
          "@type": "sc:Canvas",
          "label": "[62]",
          "metadata": [
            {
              "label": "confidence",
              "value": 0.9338141084
            }
          ],
          "thumbnail": "https://nakamura196.github.io/ki2/files/medium/waseda-i05_01646_0015/00061.jpg"
        },
        {
          "@id": "https://nakamura196.github.io/ki2/iiif/waseda-i05_01646_0015/canvas/p131#xywh=30,24,585,961",
          "@type": "sc:Canvas",
          "label": "[63]",
          "metadata": [
            {
              "label": "confidence",
              "value": 0.9209702611
            }
          ],
          "thumbnail": "https://nakamura196.github.io/ki2/files/medium/waseda-i05_01646_0015/00062.jpg"
        },
        {
          "@id": "https://nakamura196.github.io/ki2/iiif/waseda-i05_01646_0015/canvas/p142#xywh=9,0,918,679",
          "@type": "sc:Canvas",
          "label": "[64]",
          "metadata": [
            {
              "label": "confidence",
              "value": 0.9424909949
            }
          ],
          "thumbnail": "https://nakamura196.github.io/ki2/files/medium/waseda-i05_01646_0015/00063.jpg"
        },
        {
          "@id": "https://nakamura196.github.io/ki2/iiif/waseda-i05_01646_0015/canvas/p141#xywh=6,0,909,682",
          "@type": "sc:Canvas",
          "label": "[65]",
          "metadata": [
            {
              "label": "confidence",
              "value": 0.928728044
            }
          ],
          "thumbnail": "https://nakamura196.github.io/ki2/files/medium/waseda-i05_01646_0015/00064.jpg"
        },
        {
          "@id": "https://nakamura196.github.io/ki2/iiif/waseda-i05_01646_0015/canvas/p140#xywh=31,33,962,366",
          "@type": "sc:Canvas",
          "label": "[66]",
          "metadata": [
            {
              "label": "confidence",
              "value": 0.9125119448
            }
          ],
          "thumbnail": "https://nakamura196.github.io/ki2/files/medium/waseda-i05_01646_0015/00065.jpg"
        },
        {
          "@id": "https://nakamura196.github.io/ki2/iiif/waseda-i05_01646_0015/canvas/p139#xywh=18,0,642,797",
          "@type": "sc:Canvas",
          "label": "[67]",
          "metadata": [
            {
              "label": "confidence",
              "value": 0.9517916441
            }
          ],
          "thumbnail": "https://nakamura196.github.io/ki2/files/medium/waseda-i05_01646_0015/00066.jpg"
        },
        {
          "@id": "https://nakamura196.github.io/ki2/iiif/waseda-i05_01646_0015/canvas/p150#xywh=10,12,952,646",
          "@type": "sc:Canvas",
          "label": "[68]",
          "metadata": [
            {
              "label": "confidence",
              "value": 0.9183703065
            }
          ],
          "thumbnail": "https://nakamura196.github.io/ki2/files/medium/waseda-i05_01646_0015/00067.jpg"
        },
        {
          "@id": "https://nakamura196.github.io/ki2/iiif/waseda-i05_01646_0015/canvas/p149#xywh=24,11,918,644",
          "@type": "sc:Canvas",
          "label": "[69]",
          "metadata": [
            {
              "label": "confidence",
              "value": 0.9315328002
            }
          ],
          "thumbnail": "https://nakamura196.github.io/ki2/files/medium/waseda-i05_01646_0015/00068.jpg"
        },
        {
          "@id": "https://nakamura196.github.io/ki2/iiif/waseda-i05_01646_0015/canvas/p148#xywh=17,19,657,905",
          "@type": "sc:Canvas",
          "label": "[70]",
          "metadata": [
            {
              "label": "confidence",
              "value": 0.9255204797
            }
          ],
          "thumbnail": "https://nakamura196.github.io/ki2/files/medium/waseda-i05_01646_0015/00069.jpg"
        },
        {
          "@id": "https://nakamura196.github.io/ki2/iiif/waseda-i05_01646_0015/canvas/p147#xywh=30,67,845,567",
          "@type": "sc:Canvas",
          "label": "[71]",
          "metadata": [
            {
              "label": "confidence",
              "value": 0.9147900939
            }
          ],
          "thumbnail": "https://nakamura196.github.io/ki2/files/medium/waseda-i05_01646_0015/00070.jpg"
        },
        {
          "@id": "https://nakamura196.github.io/ki2/iiif/waseda-i05_01646_0015/canvas/p158#xywh=12,3,1011,668",
          "@type": "sc:Canvas",
          "label": "[72]",
          "metadata": [
            {
              "label": "confidence",
              "value": 0.9196998477
            }
          ],
          "thumbnail": "https://nakamura196.github.io/ki2/files/medium/waseda-i05_01646_0015/00071.jpg"
        },
        {
          "@id": "https://nakamura196.github.io/ki2/iiif/waseda-i05_01646_0015/canvas/p157#xywh=11,25,997,617",
          "@type": "sc:Canvas",
          "label": "[73]",
          "metadata": [
            {
              "label": "confidence",
              "value": 0.9072250724
            }
          ],
          "thumbnail": "https://nakamura196.github.io/ki2/files/medium/waseda-i05_01646_0015/00072.jpg"
        },
        {
          "@id": "https://nakamura196.github.io/ki2/iiif/waseda-i05_01646_0015/canvas/p156#xywh=21,11,978,661",
          "@type": "sc:Canvas",
          "label": "[74]",
          "metadata": [
            {
              "label": "confidence",
              "value": 0.9364478588
            }
          ],
          "thumbnail": "https://nakamura196.github.io/ki2/files/medium/waseda-i05_01646_0015/00073.jpg"
        },
        {
          "@id": "https://nakamura196.github.io/ki2/iiif/waseda-i05_01646_0015/canvas/p155#xywh=0,11,969,653",
          "@type": "sc:Canvas",
          "label": "[75]",
          "metadata": [
            {
              "label": "confidence",
              "value": 0.9251652956
            }
          ],
          "thumbnail": "https://nakamura196.github.io/ki2/files/medium/waseda-i05_01646_0015/00074.jpg"
        },
        {
          "@id": "https://nakamura196.github.io/ki2/iiif/waseda-i05_01646_0015/canvas/p166#xywh=32,34,611,845",
          "@type": "sc:Canvas",
          "label": "[76]",
          "metadata": [
            {
              "label": "confidence",
              "value": 0.9403980374
            }
          ],
          "thumbnail": "https://nakamura196.github.io/ki2/files/medium/waseda-i05_01646_0015/00075.jpg"
        },
        {
          "@id": "https://nakamura196.github.io/ki2/iiif/waseda-i05_01646_0015/canvas/p165#xywh=46,62,855,586",
          "@type": "sc:Canvas",
          "label": "[77]",
          "metadata": [
            {
              "label": "confidence",
              "value": 0.9144156575
            }
          ],
          "thumbnail": "https://nakamura196.github.io/ki2/files/medium/waseda-i05_01646_0015/00076.jpg"
        },
        {
          "@id": "https://nakamura196.github.io/ki2/iiif/waseda-i05_01646_0015/canvas/p164#xywh=9,42,915,601",
          "@type": "sc:Canvas",
          "label": "[78]",
          "metadata": [
            {
              "label": "confidence",
              "value": 0.9026532769
            }
          ],
          "thumbnail": "https://nakamura196.github.io/ki2/files/medium/waseda-i05_01646_0015/00077.jpg"
        },
        {
          "@id": "https://nakamura196.github.io/ki2/iiif/waseda-i05_01646_0015/canvas/p163#xywh=11,32,896,614",
          "@type": "sc:Canvas",
          "label": "[79]",
          "metadata": [
            {
              "label": "confidence",
              "value": 0.8457767367
            }
          ],
          "thumbnail": "https://nakamura196.github.io/ki2/files/medium/waseda-i05_01646_0015/00078.jpg"
        },
        {
          "@id": "https://nakamura196.github.io/ki2/iiif/waseda-i05_01646_0015/canvas/p174#xywh=16,18,986,365",
          "@type": "sc:Canvas",
          "label": "[80]",
          "metadata": [
            {
              "label": "confidence",
              "value": 0.9235931635
            }
          ],
          "thumbnail": "https://nakamura196.github.io/ki2/files/medium/waseda-i05_01646_0015/00079.jpg"
        },
        {
          "@id": "https://nakamura196.github.io/ki2/iiif/waseda-i05_01646_0015/canvas/p173#xywh=342,9,666,374",
          "@type": "sc:Canvas",
          "label": "[81]",
          "metadata": [
            {
              "label": "confidence",
              "value": 0.9052336216
            }
          ],
          "thumbnail": "https://nakamura196.github.io/ki2/files/medium/waseda-i05_01646_0015/00080.jpg"
        },
        {
          "@id": "https://nakamura196.github.io/ki2/iiif/waseda-i05_01646_0015/canvas/p173#xywh=3,15,75,70",
          "@type": "sc:Canvas",
          "label": "[81]",
          "metadata": [
            {
              "label": "confidence",
              "value": 0.7471416593
            }
          ],
          "thumbnail": "https://nakamura196.github.io/ki2/files/medium/waseda-i05_01646_0015/00080.jpg"
        },
        {
          "@id": "https://nakamura196.github.io/ki2/iiif/waseda-i05_01646_0015/canvas/p172#xywh=0,35,906,631",
          "@type": "sc:Canvas",
          "label": "[82]",
          "metadata": [
            {
              "label": "confidence",
              "value": 0.9192828536
            }
          ],
          "thumbnail": "https://nakamura196.github.io/ki2/files/medium/waseda-i05_01646_0015/00081.jpg"
        },
        {
          "@id": "https://nakamura196.github.io/ki2/iiif/waseda-i05_01646_0015/canvas/p171#xywh=0,6,906,663",
          "@type": "sc:Canvas",
          "label": "[83]",
          "metadata": [
            {
              "label": "confidence",
              "value": 0.9325382113
            }
          ],
          "thumbnail": "https://nakamura196.github.io/ki2/files/medium/waseda-i05_01646_0015/00082.jpg"
        },
        {
          "@id": "https://nakamura196.github.io/ki2/iiif/waseda-i05_01646_0015/canvas/p182#xywh=4,23,903,639",
          "@type": "sc:Canvas",
          "label": "[84]",
          "metadata": [
            {
              "label": "confidence",
              "value": 0.9165654182
            }
          ],
          "thumbnail": "https://nakamura196.github.io/ki2/files/medium/waseda-i05_01646_0015/00083.jpg"
        },
        {
          "@id": "https://nakamura196.github.io/ki2/iiif/waseda-i05_01646_0015/canvas/p181#xywh=0,16,926,653",
          "@type": "sc:Canvas",
          "label": "[85]",
          "metadata": [
            {
              "label": "confidence",
              "value": 0.9381321669
            }
          ],
          "thumbnail": "https://nakamura196.github.io/ki2/files/medium/waseda-i05_01646_0015/00084.jpg"
        },
        {
          "@id": "https://nakamura196.github.io/ki2/iiif/waseda-i05_01646_0015/canvas/p180#xywh=42,10,606,728",
          "@type": "sc:Canvas",
          "label": "[86]",
          "metadata": [
            {
              "label": "confidence",
              "value": 0.8012040257
            }
          ],
          "thumbnail": "https://nakamura196.github.io/ki2/files/medium/waseda-i05_01646_0015/00085.jpg"
        },
        {
          "@id": "https://nakamura196.github.io/ki2/iiif/waseda-i05_01646_0015/canvas/p179#xywh=26,4,627,752",
          "@type": "sc:Canvas",
          "label": "[87]",
          "metadata": [
            {
              "label": "confidence",
              "value": 0.9254209399
            }
          ],
          "thumbnail": "https://nakamura196.github.io/ki2/files/medium/waseda-i05_01646_0015/00086.jpg"
        },
        {
          "@id": "https://nakamura196.github.io/ki2/iiif/waseda-i05_01646_0015/canvas/p190#xywh=28,21,597,988",
          "@type": "sc:Canvas",
          "label": "[88]",
          "metadata": [
            {
              "label": "confidence",
              "value": 0.9150835872
            }
          ],
          "thumbnail": "https://nakamura196.github.io/ki2/files/medium/waseda-i05_01646_0015/00087.jpg"
        },
        {
          "@id": "https://nakamura196.github.io/ki2/iiif/waseda-i05_01646_0015/canvas/p189#xywh=0,19,817,642",
          "@type": "sc:Canvas",
          "label": "[89]",
          "metadata": [
            {
              "label": "confidence",
              "value": 0.9385061264
            }
          ],
          "thumbnail": "https://nakamura196.github.io/ki2/files/medium/waseda-i05_01646_0015/00088.jpg"
        },
        {
          "@id": "https://nakamura196.github.io/ki2/iiif/waseda-i05_01646_0015/canvas/p188#xywh=17,20,645,698",
          "@type": "sc:Canvas",
          "label": "[90]",
          "metadata": [
            {
              "label": "confidence",
              "value": 0.9208122492
            }
          ],
          "thumbnail": "https://nakamura196.github.io/ki2/files/medium/waseda-i05_01646_0015/00089.jpg"
        },
        {
          "@id": "https://nakamura196.github.io/ki2/iiif/waseda-i05_01646_0015/canvas/p187#xywh=29,37,797,619",
          "@type": "sc:Canvas",
          "label": "[91]",
          "metadata": [
            {
              "label": "confidence",
              "value": 0.9244689345
            }
          ],
          "thumbnail": "https://nakamura196.github.io/ki2/files/medium/waseda-i05_01646_0015/00090.jpg"
        },
        {
          "@id": "https://nakamura196.github.io/ki2/iiif/waseda-i05_01646_0015/canvas/p198#xywh=11,35,502,961",
          "@type": "sc:Canvas",
          "label": "[92]",
          "metadata": [
            {
              "label": "confidence",
              "value": 0.8442003727
            }
          ],
          "thumbnail": "https://nakamura196.github.io/ki2/files/medium/waseda-i05_01646_0015/00091.jpg"
        },
        {
          "@id": "https://nakamura196.github.io/ki2/iiif/waseda-i05_01646_0015/canvas/p197#xywh=10,7,660,276",
          "@type": "sc:Canvas",
          "label": "[93]",
          "metadata": [
            {
              "label": "confidence",
              "value": 0.9271652699
            }
          ],
          "thumbnail": "https://nakamura196.github.io/ki2/files/medium/waseda-i05_01646_0015/00092.jpg"
        },
        {
          "@id": "https://nakamura196.github.io/ki2/iiif/waseda-i05_01646_0015/canvas/p196#xywh=21,18,358,979",
          "@type": "sc:Canvas",
          "label": "[94]",
          "metadata": [
            {
              "label": "confidence",
              "value": 0.8732259274
            }
          ],
          "thumbnail": "https://nakamura196.github.io/ki2/files/medium/waseda-i05_01646_0015/00093.jpg"
        },
        {
          "@id": "https://nakamura196.github.io/ki2/iiif/waseda-i05_01646_0015/canvas/p195#xywh=7,0,370,990",
          "@type": "sc:Canvas",
          "label": "[95]",
          "metadata": [
            {
              "label": "confidence",
              "value": 0.892321825
            }
          ],
          "thumbnail": "https://nakamura196.github.io/ki2/files/medium/waseda-i05_01646_0015/00094.jpg"
        },
        {
          "@id": "https://nakamura196.github.io/ki2/iiif/waseda-i05_01646_0015/canvas/p206#xywh=32,50,314,854",
          "@type": "sc:Canvas",
          "label": "[96]",
          "metadata": [
            {
              "label": "confidence",
              "value": 0.9038805962
            }
          ],
          "thumbnail": "https://nakamura196.github.io/ki2/files/medium/waseda-i05_01646_0015/00095.jpg"
        },
        {
          "@id": "https://nakamura196.github.io/ki2/iiif/waseda-i05_01646_0015/canvas/p205#xywh=27,19,467,979",
          "@type": "sc:Canvas",
          "label": "[97]",
          "metadata": [
            {
              "label": "confidence",
              "value": 0.9184114933
            }
          ],
          "thumbnail": "https://nakamura196.github.io/ki2/files/medium/waseda-i05_01646_0015/00096.jpg"
        },
        {
          "@id": "https://nakamura196.github.io/ki2/iiif/waseda-i05_01646_0015/canvas/p204#xywh=8,14,459,994",
          "@type": "sc:Canvas",
          "label": "[98]",
          "metadata": [
            {
              "label": "confidence",
              "value": 0.881155014
            }
          ],
          "thumbnail": "https://nakamura196.github.io/ki2/files/medium/waseda-i05_01646_0015/00097.jpg"
        },
        {
          "@id": "https://nakamura196.github.io/ki2/iiif/waseda-i05_01646_0015/canvas/p203#xywh=283,14,729,427",
          "@type": "sc:Canvas",
          "label": "[99]",
          "metadata": [
            {
              "label": "confidence",
              "value": 0.9228262901
            }
          ],
          "thumbnail": "https://nakamura196.github.io/ki2/files/medium/waseda-i05_01646_0015/00098.jpg"
        },
        {
          "@id": "https://nakamura196.github.io/ki2/iiif/waseda-i05_01646_0015/canvas/p203#xywh=3,2,56,86",
          "@type": "sc:Canvas",
          "label": "[99]",
          "metadata": [
            {
              "label": "confidence",
              "value": 0.4144521952
            }
          ],
          "thumbnail": "https://nakamura196.github.io/ki2/files/medium/waseda-i05_01646_0015/00098.jpg"
        }
      ],
      "within": {
        "@id": "https://nakamura196.github.io/ki2/iiif/waseda-i05_01646_0015/manifest.json",
        "@type": "sc:Manifest",
        "label": ""
      }
    }
  ]
}